{
  "frames": {
    "1_1": {
      "rectangle": {
        "x": 0,
        "y": 0,
        "w": 25,
        "h": 33
      },
      "source_rectangle": {
        "x": 0,
        "y": 0,
        "w": 25,
        "h": 33
      }
    },
    "1_2": {
      "rectangle": {
        "x": 0,
        "y": 0,
        "w": 25,
        "h": 33
      },
      "source_rectangle": {
        "x": 25,
        "y": 0,
        "w": 25,
        "h": 33
      }
    },
    "1_3": {
      "rectangle": {
        "x": 0,
        "y": 0,
        "w": 25,
        "h": 33
      },
      "source_rectangle": {
        "x": 50,
        "y": 0,
        "w": 25,
        "h": 33
      }
    },
    "1_4": {
      "rectangle": {
        "x": 0,
        "y": 0,
        "w": 25,
        "h": 33
      },
      "source_rectangle": {
        "x": 75,
        "y": 0,
        "w": 25,
        "h": 33
      }
    },
    "1_5": {
      "rectangle": {
        "x": 0,
        "y": 0,
        "w": 25,
        "h": 33
      },
      "source_rectangle": {
        "x": 100,
        "y": 0,
        "w": 25,
        "h": 33
      }
    },
    "1_6": {
      "rectangle": {
        "x": 0,
        "y": 0,
        "w": 25,
        "h": 33
      },
      "source_rectangle": {
        "x": 125,
        "y": 0,
        "w": 25,
        "h": 33
      }
    },
    "1_7": {
      "rectangle": {
        "x": 0,
        "y": 0,
        "w": 25,
        "h": 33
      },
      "source_rectangle": {
        "x": 150,
        "y": 0,
        "w": 25,
        "h": 33
      }
    },
    "1_8": {
      "rectangle": {
        "x": 0,
        "y": 0,
        "w": 25,
        "h": 33
      },
      "source_rectangle": {
        "x": 175,
        "y": 0,
        "w": 25,
        "h": 33
      }
    }
  },
  "image_name": "enemy2.png"
}