{
  "frames": {
    "1_1": {
      "rectangle": {
        "x": 0,
        "y": 0,
        "w": 40,
        "h": 600
      },
      "source_rectangle": {
        "x": 0,
        "y": 0,
        "w": 40,
        "h": 600
      }
    },
    "1_2": {
      "rectangle": {
        "x": 0,
        "y": 0,
        "w": 40,
        "h": 600
      },
      "source_rectangle": {
        "x": 40,
        "y": 0,
        "w": 40,
        "h": 600
      }
    },
    "1_3": {
      "rectangle": {
        "x": 0,
        "y": 0,
        "w": 40,
        "h": 600
      },
      "source_rectangle": {
        "x": 80,
        "y": 0,
        "w": 40,
        "h": 600
      }
    },
    "1_4": {
      "rectangle": {
        "x": 0,
        "y": 0,
        "w": 40,
        "h": 600
      },
      "source_rectangle": {
        "x": 120,
        "y": 0,
        "w": 40,
        "h": 600
      }
    },
    "1_5": {
      "rectangle": {
        "x": 0,
        "y": 0,
        "w": 40,
        "h": 600
      },
      "source_rectangle": {
        "x": 160,
        "y": 0,
        "w": 40,
        "h": 600
      }
    },
    "1_6": {
      "rectangle": {
        "x": 0,
        "y": 0,
        "w": 40,
        "h": 600
      },
      "source_rectangle": {
        "x": 200,
        "y": 0,
        "w": 40,
        "h": 600
      }
    },
    "1_7": {
      "rectangle": {
        "x": 0,
        "y": 0,
        "w": 40,
        "h": 600
      },
      "source_rectangle": {
        "x": 240,
        "y": 0,
        "w": 40,
        "h": 600
      }
    },
    "1_8": {
      "rectangle": {
        "x": 0,
        "y": 0,
        "w": 40,
        "h": 600
      },
      "source_rectangle": {
        "x": 280,
        "y": 0,
        "w": 40,
        "h": 600
      }
    },
    "1_9": {
      "rectangle": {
        "x": 0,
        "y": 0,
        "w": 40,
        "h": 600
      },
      "source_rectangle": {
        "x": 320,
        "y": 0,
        "w": 40,
        "h": 600
      }
    },
    "1_10": {
      "rectangle": {
        "x": 0,
        "y": 0,
        "w": 40,
        "h": 600
      },
      "source_rectangle": {
        "x": 360,
        "y": 0,
        "w": 40,
        "h": 600
      }
    },
    "1_11": {
      "rectangle": {
        "x": 0,
        "y": 0,
        "w": 40,
        "h": 600
      },
      "source_rectangle": {
        "x": 400,
        "y": 0,
        "w": 40,
        "h": 600
      }
    },
    "1_12": {
      "rectangle": {
        "x": 0,
        "y": 0,
        "w": 40,
        "h": 600
      },
      "source_rectangle": {
        "x": 440,
        "y": 0,
        "w": 40,
        "h": 600
      }
    },
    "1_13": {
      "rectangle": {
        "x": 0,
        "y": 0,
        "w": 40,
        "h": 600
      },
      "source_rectangle": {
        "x": 480,
        "y": 0,
        "w": 40,
        "h": 600
      }
    },
    "1_14": {
      "rectangle": {
        "x": 0,
        "y": 0,
        "w": 40,
        "h": 600
      },
      "source_rectangle": {
        "x": 520,
        "y": 0,
        "w": 40,
        "h": 600
      }
    }
  },
  "image_name": "graff.png"
}